tf/__init__.py
tf/blocks.py
tf/checker.py
tf/function.py
tf/gen/__init__.py
tf/gen/grpc_controller_pb2.py
tf/gen/grpc_controller_pb2.pyi
tf/gen/grpc_controller_pb2_grpc.py
tf/gen/grpc_stdio_pb2.py
tf/gen/grpc_stdio_pb2.pyi
tf/gen/grpc_stdio_pb2_grpc.py
tf/gen/tfplugin_pb2.py
tf/gen/tfplugin_pb2.pyi
tf/gen/tfplugin_pb2_grpc.py
tf/iface.py
tf/provider.py
tf/runner.py
tf/schema.py
tf/tests/__init__.py
tf/tests/test_blocks.py
tf/tests/test_checker.py
tf/tests/test_function.py
tf/tests/test_provider.py
tf/tests/test_runner.py
tf/tests/test_schema.py
tf/tests/test_types.py
tf/tests/test_utils.py
tf/types.py
tf/utils.py
tf-1.1.0.dist-info/LICENSE
tf-1.1.0.dist-info/METADATA
tf-1.1.0.dist-info/WHEEL
tf-1.1.0.dist-info/RECORD
